[
  {
    "id": 7,
    "price": "15.5"
  },
  {
    "id": 10,
    "name": "$name",
    "price": "$price"
  },
  {
    "id": 11,
    "name": "$name",
    "price": "$price"
  },
  {
    "id": 13,
    "name": "$name",
    "price": "$price"
  },
  {
    "id": 14,
    "name": "$name",
    "price": "$price"
  },
  {
    "id": 15,
    "name": "$name",
    "price": "$price"
  },
  {
    "id": 16,
    "name": "name",
    "price": "price"
  },
  {
    "id": 17
  },
  {
    "id": 18
  },
  {
    "id": 19
  },
  {
    "id": 20
  },
  {
    "id": 21
  },
  {
    "id": 22
  },
  {
    "id": 23
  },
  {
    "id": 24
  },
  {
    "id": 25
  },
  {
    "id": 26
  },
  {
    "id": 21,
    "name": "matambre   ",
    "price": "con fritas"
  },
  {
    "id": 19,
    "name": "matambre   ",
    "price": "con fritas"
  },
  {
    "id": 20,
    "name": "matambre   ",
    "price": "con fritas"
  }
]